kedro_templar/__init__.py
kedro_templar/plugin.py
kedro_templar/process_templates.py
kedro_templar/core/__init__.py
kedro_templar/core/templates.py
kedro_templar/core/utils.py
kedro_templar-0.0.6.dist-info/LICENSE
kedro_templar-0.0.6.dist-info/METADATA
kedro_templar-0.0.6.dist-info/WHEEL
kedro_templar-0.0.6.dist-info/entry_points.txt
kedro_templar-0.0.6.dist-info/top_level.txt
kedro_templar-0.0.6.dist-info/RECORD
