Metadata-Version: 2.1
Name: kedro-templar
Version: 0.0.6
Home-page: https://github.com/webinterpret-ds/kedro-templar
Author: webinterpret-datascience
Author-email: data-science@webinterpret.com
Project-URL: Bug Tracker, https://github.com/webinterpret-ds/kedro-templar/issues
Classifier: Programming Language :: Python :: 3
Classifier: License :: OSI Approved :: GNU General Public License v3 or later (GPLv3+)
Classifier: Operating System :: OS Independent
Requires-Python: >=3.8
License-File: LICENSE
Requires-Dist: kedro (>=0.17.5)
Requires-Dist: Jinja2 (>=3.0.1)
Requires-Dist: click (<=8.0)
Requires-Dist: s3fs (<=2023.6.0)
